CHANGELOG.txt
LICENCE.txt
MANIFEST.in
README.txt
setup.py
InfSumate/__init__.py
InfSumate.egg-info/PKG-INFO
InfSumate.egg-info/SOURCES.txt
InfSumate.egg-info/dependency_links.txt
InfSumate.egg-info/top_level.txt