Metadata-Version: 2.1
Name: InfSumate
Version: 0.0.1
Summary: finds sums and partial sums of geometric series
Home-page: 
Author: Elijah Phifer
Author-email: ephifer21@gmail.com
License: MIT
Keywords: Geometric
Classifier: Development Status :: 5 - Production/Stable
Classifier: Intended Audience :: Education
Classifier: Operating System :: Microsoft :: Windows :: Windows 10
Classifier: License :: OSI Approved :: MIT License
Classifier: Programming Language :: Python :: 3
License-File: LICENCE.txt
